[null,{"name":"⠀ ⠀ ⠀ ⠀Weryfikacja","temp":"","event-type":"0","_id":"DGItI","actions":[]},{"name":"Clean Channel","temp":"message","event-type":"2","_id":"mOHJg","actions":[{"message":"1","varName":"message","info":"4","storage":"1","varName2":"message-channel","name":"Store Message Info"},{"storage":"1","varName":"message-channel","comparison":"1","value":"serverVars(\"verify-channel\")","iftrue":"0","iftrueVal":"","iffalse":"1","iffalseVal":"","name":"Check Variable"},{"server":"0","varName":"","storage":"1","varName2":"bot-member","name":"Get Bot as Member"},{"message":"1","varName":"message","info":"3","storage":"1","varName2":"message-author","name":"Store Message Info"},{"storage":"1","varName":"message-author","comparison":"1","value":"tempVars(\"bot\")","iftrue":"1","iftrueVal":"","iffalse":"0","iffalseVal":"","name":"Check Variable"},{"time":"6","measurement":"1","name":"Wait"},{"storage":"1","varName":"message","name":"Delete Message"}]},{"name":"⠀ ⠀ ⠀ ⠀ ⠀ ⠀ Inne","temp":"","event-type":"0","_id":"xyfsY","actions":[]},{"name":"MemberVoiceUpdate","temp":"prior","event-type":"22","_id":"PfnRH","actions":[{"code":"const joinChannel = serverVars(\"createVoice\");\nif (joinChannel) {\n    if (me.permissions.has('MOVE_MEMBERS')) {\n        if (me.permissions.has('MANAGE_CHANNELS')) {\n            const server = tempVars('after').guild;\n            const newUserChannel_id = tempVars(\"after\").channelID;\n            const oldUserChannel_id = tempVars(\"prior\").channelID;\n            const newUserChannel = server.channels.cache.get(newUserChannel_id);\n            const oldUserChannel = server.channels.cache.get(oldUserChannel_id);\n            const TheUser = server.members.cache.get(tempVars('after').id)\n            const parent_ID = joinChannel.parentID;\n            const Vname = TheUser.displayName + \" - prywatny\";\n            const options = {\n                type: 'voice',\n                parent: parent_ID,\n                permissionOverwrites: [{\n                    id: server.id,\n                    deny: ['CONNECT']\n                }, {\n                    id: TheUser.id,\n                    allow: ['CONNECT', 'MANAGE_ROLES']\n                }]\n            };\n\n            if (newUserChannel == joinChannel) {\n                if (oldUserChannel && oldUserChannel.name == Vname) {\n                    oldUserChannel.delete();\n                    server.channels.create(Vname, options)\n                        .then(function (channel) {\n                            TheUser.voice.setChannel(channel);\n                        }.bind(this))\n                        .catch(this.displayError.bind(this));\n                } else {\n                    server.channels.create(Vname, options)\n                        .then(function (channel) {\n                            TheUser.voice.setChannel(channel);\n                        }.bind(this))\n                        .catch(this.displayError.bind(this));\n                }\n            } else if (oldUserChannel && oldUserChannel !== joinChannel && oldUserChannel.members.size == 0 && oldUserChannel.name == Vname) {\n                oldUserChannel.delete();\n            } else if (oldUserChannel && oldUserChannel !== joinChannel && oldUserChannel.members.size == 0 && oldUserChannel.name.includes('-prywatny')) {\n                oldUserChannel.delete();\n            }\n        } else {\n            console.log('The bot is missing MANAGE_CHANNELS permission.');\n        }\n    } else {\n        console.log('The bot is missing MOVE_MEMBERS permission.');\n    }\n}","behavior":"0","interpretation":"1","storage":"0","varName":"","VTypeSelect":"0","CVTypeValue":"","name":"Run Script"}],"temp2":"after"},{"name":"streamstatus","temp":"2","event-type":"3","_id":"Nkccp","actions":[{"activity":"2","nameText":"Never gonna give you up","url":"http://twitch.tv/","stat":"1","name":"Set Bot Activity"}]}]